cv19index/__init__.py
cv19index/__main__.py
cv19index/io.py
cv19index/predict.py
cv19index/preprocess.py
cv19index/server.py
cv19index/shap_top_factors.py
cv19index/util.py
cv19index/resources/ccsrEdges.txt
cv19index/resources/ccsrNodes.txt
cv19index/resources/xgboost/input.csv.schema.json
cv19index/resources/xgboost/model.pickle
cv19index-1.0.1.dist-info/LICENSE
cv19index-1.0.1.dist-info/METADATA
cv19index-1.0.1.dist-info/WHEEL
cv19index-1.0.1.dist-info/entry_points.txt
cv19index-1.0.1.dist-info/top_level.txt
cv19index-1.0.1.dist-info/RECORD
