Metadata-Version: 2.1
Name: cv19index
Version: 1.0.1
Summary: COVID-19 Vulnerability Index
Home-page: https://cv19index.com
Author: Dave Decaprio
Author-email: dave.decaprio@closedloop.ai
License: BSD
Platform: UNKNOWN
Classifier: Development Status :: 4 - Beta
Classifier: Intended Audience :: Healthcare Industry
Classifier: Intended Audience :: Science/Research
Classifier: Intended Audience :: Developers
Classifier: Natural Language :: English
Classifier: Framework :: Jupyter
Classifier: License :: OSI Approved :: BSD License
Classifier: Programming Language :: Python :: 3.6
Classifier: Programming Language :: Python :: 3.7
Requires-Dist: numpy (==1.17.4)
Requires-Dist: pandas (==0.23.4)
Requires-Dist: setuptools (==40.2.0)
Requires-Dist: shap (==0.33)
Requires-Dist: xgboost (==1.0.1)
Requires-Dist: flask (==1.1.1)
